qauth/__init__.py
qauth-0.1.0.dist-info/METADATA
qauth-0.1.0.dist-info/WHEEL
qauth-0.1.0.dist-info/RECORD
