Metadata-Version: 2.4
Name: qauth
Version: 0.1.0
Summary: QuantumAuth - Next-generation authentication and authorization protocol with post-quantum security
Project-URL: Homepage, https://tusharagrawal.in/qauth
Project-URL: Repository, https://github.com/Tushar010402/quantum-shield
Project-URL: Documentation, https://tusharagrawal.in/qauth
Project-URL: Changelog, https://github.com/Tushar010402/quantum-shield/blob/master/qauth/CHANGELOG.md
Project-URL: Issues, https://github.com/Tushar010402/quantum-shield/issues
Author-email: Tushar Agrawal <tusharagrawal0104@gmail.com>
License: MIT
Keywords: authentication,authorization,cryptography,jwt,oauth,post-quantum,security
Classifier: Development Status :: 3 - Alpha
Classifier: Intended Audience :: Developers
Classifier: License :: OSI Approved :: MIT License
Classifier: Operating System :: OS Independent
Classifier: Programming Language :: Python :: 3
Classifier: Programming Language :: Python :: 3.9
Classifier: Programming Language :: Python :: 3.10
Classifier: Programming Language :: Python :: 3.11
Classifier: Programming Language :: Python :: 3.12
Classifier: Topic :: Internet :: WWW/HTTP :: Session
Classifier: Topic :: Security :: Cryptography
Classifier: Topic :: Software Development :: Libraries :: Python Modules
Classifier: Typing :: Typed
Requires-Python: >=3.9
Requires-Dist: cryptography>=41.0.0
Requires-Dist: pynacl>=1.5.0
Provides-Extra: dev
Requires-Dist: black>=23.0; extra == 'dev'
Requires-Dist: mypy>=1.0; extra == 'dev'
Requires-Dist: pytest-asyncio>=0.21; extra == 'dev'
Requires-Dist: pytest-cov>=4.0; extra == 'dev'
Requires-Dist: pytest>=7.0; extra == 'dev'
Requires-Dist: ruff>=0.1.0; extra == 'dev'
Requires-Dist: types-cryptography; extra == 'dev'
